dharsh_parrot-0.1.0.dist-info/licenses/LICENSE
terminal_parrot/__init__.py
terminal_parrot/main.py
terminal_parrot/animations/parrot.animation
dharsh_parrot-0.1.0.dist-info/METADATA
dharsh_parrot-0.1.0.dist-info/WHEEL
dharsh_parrot-0.1.0.dist-info/entry_points.txt
dharsh_parrot-0.1.0.dist-info/top_level.txt
dharsh_parrot-0.1.0.dist-info/RECORD
