Metadata-Version: 2.4
Name: dharsh-parrot
Version: 0.1.0
Summary: Animated Dharsh Parrot for your terminal 🦜
Author-email: Dharsini Sri <purpleunalome@gmail.com>
License-Expression: MIT
Requires-Python: >=3.7
License-File: LICENSE
Dynamic: license-file
